pyspark_delta_scd2/__init__.py
pyspark_delta_scd2/base.py
pyspark_delta_scd2/utils.py
pyspark_delta_scd2-0.4.1.dist-info/LICENSE
pyspark_delta_scd2-0.4.1.dist-info/METADATA
pyspark_delta_scd2-0.4.1.dist-info/WHEEL
pyspark_delta_scd2-0.4.1.dist-info/RECORD
