Metadata-Version: 2.1
Name: pyspark-delta-scd2
Version: 0.4.1
Summary: This project utilizes faker-pyspark to generate random schema and dataframes to mimic data table snapshots. Using these snapshots to process and apply SCD2 pattern into delta table as the destination.
Home-page: https://github.com/spsoni/pyspark-delta-scd2
License: MIT
Keywords: Faker, PySpark,DeltaTable
Author: Sury Soni
Author-email: github@suryasoni.info
Requires-Python: >=3.8.1,<4.0.0
Classifier: License :: OSI Approved :: MIT License
Classifier: Programming Language :: Python :: 3
Classifier: Programming Language :: Python :: 3.9
Classifier: Programming Language :: Python :: 3.10
Classifier: Programming Language :: Python :: 3.11
Project-URL: Repository, https://github.com/spsoni/pyspark-delta-scd2
